<?xml version="1.0"?>
<!DOCTYPE hibernate-mapping PUBLIC
        "-//Hibernate/Hibernate Mapping DTD 3.0//EN"
        "http://hibernate.sourceforge.net/hibernate-mapping-3.0.dtd">
<hibernate-mapping>
	<class entity-name="BusStation" table="Object_BusStation">
		<id name="id" type="long" column="id">
			<generator class="native" />
		</id>
		<property name="seq" type="integer" />
		<property name="busId" type="long" />
		<property name="busName" type="string" />
		<property name="stopName" type="string" />
		<property name="lat" type="double" />
		<property name="lng" type="double" />
	</class>
</hibernate-mapping>